.gitignore
.pylintrc
.readthedocs.yaml
CHANGELOG.md
LICENSE
PKG-INFO
README.md
THIRD-PARTY-LICENCES
pyproject.toml
.git_hooks/pre-commit
.github/dependabot.yml
.github/pull_request_template.md
.github/ISSUE_TEMPLATE/bug_report.yml
.github/ISSUE_TEMPLATE/documentation_update.md
.github/ISSUE_TEMPLATE/feature_request.md
.github/actions/bw_install/action.yml
.github/scripts/pr_issue_sync/pr_issue_sync.py
.github/scripts/pr_issue_sync/requirements.txt
.github/workflows/check_pr.yml
.github/workflows/child_repos.yml
.github/workflows/ci.yml
.github/workflows/end2end-conda.yml
.github/workflows/formatter.yml
.github/workflows/generate-cli-check.yml
.github/workflows/pytest-matrix.yml
.github/workflows/pytest.yml
.github/workflows/semantic_release.yml
.github/workflows/stale-issues.yml
.github/workflows/sync-issues-pr.yml
bec_widgets/__init__.py
bec_widgets/applications/__init__.py
bec_widgets/applications/bw_launch.py
bec_widgets/applications/launch_window.py
bec_widgets/assets/app_icons/BEC-General-App.png
bec_widgets/assets/app_icons/alignment_1d.png
bec_widgets/assets/app_icons/auto_update.png
bec_widgets/assets/app_icons/bec_widgets_icon.png
bec_widgets/assets/app_icons/ui_loader_tile.png
bec_widgets/assets/app_icons/widget_launch_tile.png
bec_widgets/cli/__init__.py
bec_widgets/cli/client.py
bec_widgets/cli/client_utils.py
bec_widgets/cli/generate_cli.py
bec_widgets/cli/server.py
bec_widgets/cli/rpc/__init__.py
bec_widgets/cli/rpc/rpc_base.py
bec_widgets/cli/rpc/rpc_register.py
bec_widgets/cli/rpc/rpc_widget_handler.py
bec_widgets/examples/__init__.py
bec_widgets/examples/general_app/__init__.py
bec_widgets/examples/general_app/general_app.py
bec_widgets/examples/general_app/general_app.ui
bec_widgets/examples/general_app/web_links.py
bec_widgets/examples/jupyter_console/__init__.py
bec_widgets/examples/jupyter_console/jupyter_console_window.py
bec_widgets/examples/plugin_example_pyside/__init__.py
bec_widgets/examples/plugin_example_pyside/main.py
bec_widgets-2.45.14.dist-info/METADATA
bec_widgets-2.45.14.dist-info/WHEEL
bec_widgets-2.45.14.dist-info/entry_points.txt
bec_widgets-2.45.14.dist-info/licenses/LICENSE
bec_widgets-2.45.14.dist-info/RECORD
