Metadata-Version: 2.4
Name: bec_widgets
Version: 2.45.14
Summary: BEC Widgets
Project-URL: Bug Tracker, https://gitlab.psi.ch/bec/bec_widgets/issues
Project-URL: Homepage, https://gitlab.psi.ch/bec/bec_widgets
License-File: LICENSE
Classifier: Development Status :: 3 - Alpha
Classifier: Programming Language :: Python :: 3
Classifier: Topic :: Scientific/Engineering
Requires-Python: >=3.11
Requires-Dist: bec-ipython-client~=3.70
Requires-Dist: bec-lib~=3.70
Requires-Dist: bec-qthemes>=0.7,~=0.7
Requires-Dist: black~=25.0
Requires-Dist: isort>=5.13.2,~=5.13
Requires-Dist: pydantic~=2.0
Requires-Dist: pyqtgraph==0.13.7
Requires-Dist: pyside6==6.9.0
Requires-Dist: qtconsole>=5.5.1,~=5.5
Requires-Dist: qtmonaco~=0.5
Requires-Dist: qtpy~=2.4
Requires-Dist: thefuzz~=0.22
Provides-Extra: dev
Requires-Dist: coverage~=7.0; extra == 'dev'
Requires-Dist: fakeredis>=2.23.2,~=2.23; extra == 'dev'
Requires-Dist: pre-commit~=4.2; extra == 'dev'
Requires-Dist: pytest-bec-e2e<=4.0,>=2.21.4; extra == 'dev'
Requires-Dist: pytest-cov~=6.1.1; extra == 'dev'
Requires-Dist: pytest-qt~=4.4; extra == 'dev'
Requires-Dist: pytest-random-order~=1.1; extra == 'dev'
Requires-Dist: pytest-timeout~=2.2; extra == 'dev'
Requires-Dist: pytest-xvfb~=3.0; extra == 'dev'
Requires-Dist: pytest~=8.0; extra == 'dev'
Requires-Dist: watchdog~=6.0; extra == 'dev'
